{
    "songs": [
      {
        "song": "I Will Always Love You",
        "artist": "Whitney Houston",
        "year": "1992"
      },
      {
        "song": "Smells Like Teen Spirit",
        "artist": "Nirvana",
        "year": "1991"
      },
      {
        "song": "(Everything I Do) I Do It for You",
        "artist": "Bryan Adams",
        "year": "1991"
      },
      {
        "song": "Nothing Compares 2 U",
        "artist": "Sinéad O’Connor",
        "year": "1990"
      },
      {
        "song": "My Heart Will Go On",
        "artist": "Celine Dion",
        "year": "1997"
      },
      {
        "song": "Candle in the Wind 1997 (Goodbye England’s Rose)",
        "artist": "Elton John",
        "year": "1997"
      },
      {
        "song": "Losing My Religion",
        "artist": "R.E.M.",
        "year": "1991"
      },
      {
        "song": "Wonderwall",
        "artist": "Oasis",
        "year": "1995"
      },
      {
        "song": "Macarena (Bayside Boys Mix)",
        "artist": "Los Del Rio",
        "year": "1995"
      },
      {
        "song": "One",
        "artist": "U2",
        "year": "1991"
      },
      {
        "song": "Baby One More Time",
        "artist": "Britney Spears",
        "year": "1998"
      },
      {
        "song": "Wannabe",
        "artist": "Spice Girls",
        "year": "1996"
      },
      {
        "song": "Bitter Sweet Symphony",
        "artist": "The Verve",
        "year": "1997"
      },
      {
        "song": "Smooth",
        "artist": "Santana with Rob Thomas",
        "year": "1999"
      },
      {
        "song": "I Don’t Want to Miss a Thing",
        "artist": "Aerosmith",
        "year": "1998"
      },
      {
        "song": "I’ll Make Love to You",
        "artist": "Boyz II Men",
        "year": "1994"
      },
      {
        "song": "Creep",
        "artist": "Radiohead",
        "year": "1993"
      },
      {
        "song": "Gangsta’s Paradise",
        "artist": "Coolio with L.V.",
        "year": "1995"
      },
      {
        "song": "Iris",
        "artist": "Goo Goo Dolls",
        "year": "1998"
      },
      {
        "song": "Under the Bridge",
        "artist": "Red Hot Chili Peppers",
        "year": "1992"
      },
      {
        "song": "Believe",
        "artist": "Cher",
        "year": "1998"
      },
      {
        "song": "I’ll Be Missing You",
        "artist": "Puff Daddy with Faith Evans & 112",
        "year": "1997"
      },
      {
        "song": "One Sweet Day",
        "artist": "Mariah Carey with Boyz II Men",
        "year": "1995"
      },
      {
        "song": "You’re Still the One",
        "artist": "Shania Twain",
        "year": "1998"
      },
      {
        "song": "End of the Road",
        "artist": "Boyz II Men",
        "year": "1992"
      },
      {
        "song": "Because You Loved Me",
        "artist": "Celine Dion",
        "year": "1996"
      },
      {
        "song": "Loser",
        "artist": "Beck",
        "year": "1993"
      },
      {
        "song": "Jeremy",
        "artist": "Pearl Jam",
        "year": "1992"
      },
      {
        "song": "Don’t Speak",
        "artist": "No Doubt",
        "year": "1996"
      },
      {
        "song": "Vogue",
        "artist": "Madonna",
        "year": "1990"
      },
      {
        "song": "Tears in Heaven",
        "artist": "Eric Clapton",
        "year": "1992"
      },
      {
        "song": "Live Forever",
        "artist": "Oasis",
        "year": "1994"
      },
      {
        "song": "You Oughta Know",
        "artist": "Alanis Morissette",
        "year": "1995"
      },
      {
        "song": "Baby Got Back",
        "artist": "Sir Mix-A-Lot",
        "year": "1992"
      },
      {
        "song": "Torn",
        "artist": "Natalie Imbruglia",
        "year": "1997"
      },
      {
        "song": "Amazed",
        "artist": "Lonestar",
        "year": "1999"
      },
      {
        "song": "Waterfalls",
        "artist": "TLC",
        "year": "1995"
      },
      {
        "song": "Kiss from a Rose",
        "artist": "Seal",
        "year": "1994"
      },
      {
        "song": "Un-Break My Heart",
        "artist": "Toni Braxton",
        "year": "1996"
      },
      {
        "song": "Enter Sandman",
        "artist": "Metallica",
        "year": "1991"
      },
      {
        "song": "All I Want for Christmas Is You",
        "artist": "Mariah Carey",
        "year": "1994"
      },
      {
        "song": "U Can’t Touch This",
        "artist": "MC Hammer",
        "year": "1990"
      },
      {
        "song": "I’d Do Anything for Love (But I Won’t Do That)",
        "artist": "Meat Loaf",
        "year": "1993"
      },
      {
        "song": "Common People",
        "artist": "Pulp",
        "year": "1995"
      },
      {
        "song": "Everybody Hurts",
        "artist": "R.E.M.",
        "year": "1993"
      },
      {
        "song": "Friends in Low Places",
        "artist": "Garth Brooks",
        "year": "1990"
      },
      {
        "song": "November Rain",
        "artist": "Guns N’ Roses",
        "year": "1991"
      },
      {
        "song": "Ironic",
        "artist": "Alanis Morissette",
        "year": "1996"
      },
      {
        "song": "I Swear",
        "artist": "All-4-One",
        "year": "1994"
      },
      {
        "song": "Ice Ice Baby",
        "artist": "Vanilla Ice",
        "year": "1990"
      },
      {
        "song": "Livin’ La Vida Loca",
        "artist": "Ricky Martin",
        "year": "1999"
      },
      {
        "song": "Song 2",
        "artist": "Blur",
        "year": "1997"
      },
      {
        "song": "That’s the Way Love Goes",
        "artist": "Janet Jackson",
        "year": "1993"
      },
      {
        "song": "Truly, Madly, Deeply",
        "artist": "Savage Garden",
        "year": "1997"
      },
      {
        "song": "No Scrubs",
        "artist": "TLC",
        "year": "1999"
      },
      {
        "song": "All I Wanna Do",
        "artist": "Sheryl Crow",
        "year": "1993"
      },
      {
        "song": "Mambo No. 5 (A Little Bit of…)",
        "artist": "Lou Bega",
        "year": "1999"
      },
      {
        "song": "Unforgettable",
        "artist": "Natalie Cole with Nat “King” Cole",
        "year": "1991"
      },
      {
        "song": "Black Hole Sun",
        "artist": "Soundgarden",
        "year": "1994"
      },
      {
        "song": "Good Riddance (Time of Your Life)",
        "artist": "Green Day",
        "year": "1997"
      },
      {
        "song": "Streets of Philadelphia",
        "artist": "Bruce Springsteen",
        "year": "1994"
      },
      {
        "song": "Vision of Love",
        "artist": "Mariah Carey",
        "year": "1990"
      },
      {
        "song": "The Sign",
        "artist": "Ace of Base",
        "year": "1994"
      },
      {
        "song": "Alive",
        "artist": "Pearl Jam",
        "year": "1991"
      },
      {
        "song": "Hallelujah",
        "artist": "Jeff Buckley",
        "year": "1994"
      },
      {
        "song": "Don’t Look Back in Anger",
        "artist": "Oasis",
        "year": "1996"
      },
      {
        "song": "Champagne Supernova",
        "artist": "Oasis",
        "year": "1995"
      },
      {
        "song": "Mmmbop",
        "artist": "Hanson",
        "year": "1997"
      },
      {
        "song": "Come As You Are",
        "artist": "Nirvana",
        "year": "1991"
      },
      {
        "song": "The Boy Is Mine",
        "artist": "Brandy & Monica",
        "year": "1998"
      },
      {
        "song": "A Whole New World",
        "artist": "Peabo Bryson with Regina Belle",
        "year": "1992"
      },
      {
        "song": "Gonna Make You Sweat (Everybody Dance Now)",
        "artist": "C + C Music Factory",
        "year": "1990"
      },
      {
        "song": "Jump",
        "artist": "Kris Kross",
        "year": "1992"
      },
      {
        "song": "Enjoy the Silence",
        "artist": "Depeche Mode",
        "year": "1990"
      },
      {
        "song": "Doo Wop (That Thing)",
        "artist": "Lauryn Hill",
        "year": "1998"
      },
      {
        "song": "Achy Breaky Heart",
        "artist": "Billy Ray Cyrus",
        "year": "1992"
      },
      {
        "song": "This Is How We Do It",
        "artist": "Montell Jordan",
        "year": "1995"
      },
      {
        "song": "Take a Bow",
        "artist": "Madonna",
        "year": "1994"
      },
      {
        "song": "Say My Name",
        "artist": "Destiny’s Child",
        "year": "1999"
      },
      {
        "song": "Jump Around",
        "artist": "House of Pain",
        "year": "1992"
      },
      {
        "song": "Bakset Case",
        "artist": "Green Day",
        "year": "1994"
      },
      {
        "song": "Fantasy",
        "artist": "Mariah Carey",
        "year": "1995"
      },
      {
        "song": "Nuthin’ But a G Thang",
        "artist": "Dr. Dre with Snoop Doggy Dogg",
        "year": "1992"
      },
      {
        "song": "No Diggity",
        "artist": "Blackstreet with Dr. Dre",
        "year": "1995"
      },
      {
        "song": "Dreamlover",
        "artist": "Mariah Carey",
        "year": "1993"
      },
      {
        "song": "I Believe I Can Fly",
        "artist": "R. Kelly",
        "year": "1996"
      },
      {
        "song": "I Love You Always Forever",
        "artist": "Donna Lewis",
        "year": "1996"
      },
      {
        "song": "How Do I Live",
        "artist": "LeAnn Rimes",
        "year": "1997"
      },
      {
        "song": "I Want It That Way",
        "artist": "Backstreet Boys",
        "year": "1999"
      },
      {
        "song": "Save the Best for Last",
        "artist": "Vanessa Williams",
        "year": "1992"
      },
      {
        "song": "Black or White",
        "artist": "Michael Jackson",
        "year": "1991"
      },
      {
        "song": "1979",
        "artist": "Smashing Pumpkins",
        "year": "1995"
      },
      {
        "song": "Paranoid Android",
        "artist": "Radiohead",
        "year": "1997"
      },
      {
        "song": "Heart Shaped Box",
        "artist": "Nirvana",
        "year": "1993"
      },
      {
        "song": "Hero",
        "artist": "Mariah Carey",
        "year": "1993"
      },
      {
        "song": "All Apologies",
        "artist": "Nirvana",
        "year": "1993"
      },
      {
        "song": "Tubthumping",
        "artist": "Chumbawamba",
        "year": "1997"
      },
      {
        "song": "It Must Have Been Love",
        "artist": "Roxette",
        "year": "1990"
      },
      {
        "song": "With Arms Wide Open",
        "artist": "Creed",
        "year": "1999"
      },
      {
        "song": "Angels",
        "artist": "Robbie Williams",
        "year": "1997"
      }
    ]
  }
  